veilgen/__init__.py
veilgen/veilgen.py
veilgen-1.0.0.dist-info/METADATA
veilgen-1.0.0.dist-info/WHEEL
veilgen-1.0.0.dist-info/entry_points.txt
veilgen-1.0.0.dist-info/top_level.txt
veilgen-1.0.0.dist-info/RECORD
