Metadata-Version: 2.2
Name: veilgen
Version: 1.0.0
Summary: A powerful tool for generating fake data for cybersecurity testing and development.
Home-page: https://github.com/hexa-01/Veilgen-Master
Author: hexa-01
Author-email: veilgen@proton.me
Classifier: Programming Language :: Python :: 3
Classifier: License :: OSI Approved :: MIT License
Classifier: Operating System :: OS Independent
Requires-Python: >=3.6
Requires-Dist: rich
Requires-Dist: cryptography
Requires-Dist: faker
Dynamic: author
Dynamic: author-email
Dynamic: classifier
Dynamic: description
Dynamic: description-content-type
Dynamic: home-page
Dynamic: requires-dist
Dynamic: requires-python
Dynamic: summary
